mlox/__init__.py
mlox/app.py
mlox/cli.py
mlox/config.py
mlox/infra.py
mlox/remote.py
mlox/secret_manager.py
mlox/server.py
mlox/service.py
mlox/session.py
mlox/utils.py
mlox/assets/__init__.py
mlox/assets/cloud-init.yaml
mlox/assets/start-multipass.sh
mlox/integrations/__init__.py
mlox/integrations/gcp/__init__.py
mlox/integrations/gcp/secret_manager.py
mlox/resources/__init__.py
mlox/resources/mlox.png
mlox/resources/mlox_logo.png
mlox/resources/mlox_logo_small.png
mlox/resources/mlox_logo_wide.png
mlox/servers/__init__.py
mlox/servers/ubuntu/__init__.py
mlox/servers/ubuntu/docker.py
mlox/servers/ubuntu/k3s.py
mlox/servers/ubuntu/native.py
mlox/servers/ubuntu/ui_docker.py
mlox/servers/ubuntu/ui_k3s.py
mlox/servers/ubuntu/ui_native.py
mlox/services/__init__.py
mlox/services/utils_ui.py
mlox/services/airflow/__init__.py
mlox/services/airflow/docker.py
mlox/services/airflow/ui.py
mlox/services/gcp_secrets/__init__.py
mlox/services/gcp_secrets/secret_manager.py
mlox/services/gcp_secrets/service.py
mlox/services/gcp_secrets/ui.py
mlox/services/github/__init__.py
mlox/services/github/service.py
mlox/services/github/ui.py
mlox/services/influx/__init__.py
mlox/services/influx/docker.py
mlox/services/influx/ui.py
mlox/services/k8s_dashboard/__init__.py
mlox/services/k8s_dashboard/k8s.py
mlox/services/k8s_dashboard/ui.py
mlox/services/k8s_headlamp/__init__.py
mlox/services/k8s_headlamp/k8s.py
mlox/services/k8s_headlamp/ui.py
mlox/services/kubeapps/__init__.py
mlox/services/kubeapps/k8s.py
mlox/services/kubeapps/ui.py
mlox/services/litellm/__init__.py
mlox/services/litellm/docker.py
mlox/services/litellm/ui.py
mlox/services/mlflow/__init__.py
mlox/services/mlflow/docker.py
mlox/services/mlflow/mlops_example.py
mlox/services/mlflow/models.py
mlox/services/mlflow/serve.py
mlox/services/mlflow/ui.py
mlox/services/mlflow_mlserver/__init__.py
mlox/services/mlflow_mlserver/docker.py
mlox/services/mlflow_mlserver/ui.py
mlox/services/otel/__init__.py
mlox/services/otel/docker.py
mlox_demo-0.1.0.post5.dist-info/licenses/LICENSE
mlox_demo-0.1.0.post5.dist-info/METADATA
mlox_demo-0.1.0.post5.dist-info/WHEEL
mlox_demo-0.1.0.post5.dist-info/entry_points.txt
mlox_demo-0.1.0.post5.dist-info/top_level.txt
mlox_demo-0.1.0.post5.dist-info/RECORD
