Metadata-Version: 2.4
Name: mlox-demo
Version: 0.1.0.post5
Summary: MLOps Platform for Data Scientists and Engineers to build, deploy and manage machine learning applications and more.
Author-email: nicococo <contact@mlox.org>
License: MIT License
Project-URL: Homepage, https://github.com/nicococo/mlox
Project-URL: Tracker, https://github.com/nicococo/mlox/issues
Project-URL: Source, https://github.com/nicococo/mlox
Project-URL: Examples, https://github.com/nicococo/mlox
Keywords: Infrastructure,Server,Service,Dashboard,Opinionated,MLOps
Classifier: Development Status :: 3 - Alpha
Classifier: Intended Audience :: Developers
Classifier: Topic :: Software Development
Classifier: Topic :: System :: Distributed Computing
Classifier: Topic :: Internet
Classifier: Topic :: Database
Classifier: Programming Language :: Python :: 3
Classifier: License :: OSI Approved :: MIT License
Classifier: Operating System :: OS Independent
Requires-Python: >=3.11
License-File: LICENSE
Requires-Dist: dacite
Requires-Dist: pyyaml
Requires-Dist: fabric
Requires-Dist: cryptography
Requires-Dist: bcrypt
Requires-Dist: passlib
Provides-Extra: ui
Requires-Dist: streamlit; extra == "ui"
Requires-Dist: streamlit-vis-timeline; extra == "ui"
Requires-Dist: pandas; extra == "ui"
Requires-Dist: numpy; extra == "ui"
Provides-Extra: ml
Requires-Dist: mlflow; extra == "ml"
Requires-Dist: mlserver; extra == "ml"
Requires-Dist: psutil; extra == "ml"
Provides-Extra: gcp
Requires-Dist: google-cloud-secret-manager; extra == "gcp"
Requires-Dist: oauth2client; extra == "gcp"
Provides-Extra: telemetry
Requires-Dist: opentelemetry-api; extra == "telemetry"
Requires-Dist: opentelemetry-sdk; extra == "telemetry"
Requires-Dist: opentelemetry-exporter-otlp; extra == "telemetry"
Provides-Extra: connectors
Requires-Dist: redis; extra == "connectors"
Requires-Dist: grpcio; extra == "connectors"
Provides-Extra: all
Requires-Dist: mlox-demo[connectors,gcp,ml,telemetry,ui]; extra == "all"
Provides-Extra: dev
Requires-Dist: mlox-demo[all]; extra == "dev"
Requires-Dist: pytest; extra == "dev"
Requires-Dist: pytest-cov; extra == "dev"
Requires-Dist: flake8; extra == "dev"
Requires-Dist: build; extra == "dev"
Requires-Dist: twine; extra == "dev"
Dynamic: license-file
